dingz/__init__.py
dingz/cli.py
dingz/constants.py
dingz/dimmer.py
dingz/dingz.py
dingz/discovery.py
dingz/exceptions.py
dingz/registry.py
dingz/shade.py
dingz-0.5.0.dist-info/LICENSE
dingz-0.5.0.dist-info/METADATA
dingz-0.5.0.dist-info/WHEEL
dingz-0.5.0.dist-info/entry_points.txt
dingz-0.5.0.dist-info/top_level.txt
dingz-0.5.0.dist-info/zip-safe
dingz-0.5.0.dist-info/RECORD
