Metadata-Version: 2.1
Name: dingz
Version: 0.5.0
Summary: Python API for interacting with Dingz devices
Home-page: https://github.com/home-assistant-ecosystem/python-dingz
Author: Fabian Affolter
Author-email: fabian@affolter-engineering.ch
License: Apache License 2.0
Platform: UNKNOWN
Classifier: Development Status :: 3 - Alpha
Classifier: Environment :: Console
Classifier: Intended Audience :: Developers
Classifier: License :: OSI Approved :: Apache Software License
Classifier: Operating System :: MacOS :: MacOS X
Classifier: Operating System :: Microsoft :: Windows
Classifier: Operating System :: POSIX
Classifier: Programming Language :: Python :: 3.8
Classifier: Programming Language :: Python :: 3.9
Classifier: Topic :: Utilities
Requires-Python: >=3.8
License-File: LICENSE
Requires-Dist: aiohttp (<4)
Requires-Dist: async-timeout (<5)
Requires-Dist: click
Requires-Dist: setuptools
